{
  "update_time": "2026-06-12 16:54:44",
  "sources": [
    {
      "name": "微博热搜",
      "items": [
        {
          "rank": 0,
          "title": "世界杯在中国的收视率爆了",
          "url": "https://s.weibo.com/weibo?q=%E4%B8%96%E7%95%8C%E6%9D%AF%E5%9C%A8%E4%B8%AD%E5%9B%BD%E7%9A%84%E6%94%B6%E8%A7%86%E7%8E%87%E7%88%86%E4%BA%86",
          "hot": 0,
          "tag": ""
        },
        {
          "rank": 1,
          "title": "老外也疑惑中国为什么不参加世界杯",
          "url": "https://s.weibo.com/weibo?q=%E8%80%81%E5%A4%96%E4%B9%9F%E7%96%91%E6%83%91%E4%B8%AD%E5%9B%BD%E4%B8%BA%E4%BB%80%E4%B9%88%E4%B8%8D%E5%8F%82%E5%8A%A0%E4%B8%96%E7%95%8C%E6%9D%AF",
          "hot": 0,
          "tag": ""
        },
        {
          "rank": 2,
          "title": "打卡中国",
          "url": "https://s.weibo.com/weibo?q=%E6%89%93%E5%8D%A1%E4%B8%AD%E5%9B%BD",
          "hot": 0,
          "tag": ""
        },
        {
          "rank": 2,
          "title": "看球上京东猜中冠军抽百万份免单",
          "url": "https://s.weibo.com/weibo?q=%E7%9C%8B%E7%90%83%E4%B8%8A%E4%BA%AC%E4%B8%9C%E7%8C%9C%E4%B8%AD%E5%86%A0%E5%86%9B%E6%8A%BD%E7%99%BE%E4%B8%87%E4%BB%BD%E5%85%8D%E5%8D%95",
          "hot": 0,
          "tag": ""
        },
        {
          "rank": 3,
          "title": "买连衣裙 看手肘",
          "url": "https://s.weibo.com/weibo?q=%E4%B9%B0%E8%BF%9E%E8%A1%A3%E8%A3%99%20%E7%9C%8B%E6%89%8B%E8%82%98",
          "hot": 0,
          "tag": ""
        },
        {
          "rank": 4,
          "title": "25岁女子为保胎多器官衰竭进ICU",
          "url": "https://s.weibo.com/weibo?q=25%E5%B2%81%E5%A5%B3%E5%AD%90%E4%B8%BA%E4%BF%9D%E8%83%8E%E5%A4%9A%E5%99%A8%E5%AE%98%E8%A1%B0%E7%AB%AD%E8%BF%9BICU",
          "hot": 0,
          "tag": ""
        },
        {
          "rank": 5,
          "title": "内娱闯不进去的赛道短剧闯进去了",
          "url": "https://s.weibo.com/weibo?q=%E5%86%85%E5%A8%B1%E9%97%AF%E4%B8%8D%E8%BF%9B%E5%8E%BB%E7%9A%84%E8%B5%9B%E9%81%93%E7%9F%AD%E5%89%A7%E9%97%AF%E8%BF%9B%E5%8E%BB%E4%BA%86",
          "hot": 0,
          "tag": ""
        },
        {
          "rank": 5,
          "title": "中国MPV世家看传祺",
          "url": "https://s.weibo.com/weibo?q=%E4%B8%AD%E5%9B%BDMPV%E4%B8%96%E5%AE%B6%E7%9C%8B%E4%BC%A0%E7%A5%BA",
          "hot": 0,
          "tag": ""
        },
        {
          "rank": 6,
          "title": "念一辈子本科",
          "url": "https://s.weibo.com/weibo?q=%E5%BF%B5%E4%B8%80%E8%BE%88%E5%AD%90%E6%9C%AC%E7%A7%91",
          "hot": 0,
          "tag": ""
        },
        {
          "rank": 7,
          "title": "张月选安崎投了40票而淡淡投了0",
          "url": "https://s.weibo.com/weibo?q=%E5%BC%A0%E6%9C%88%E9%80%89%E5%AE%89%E5%B4%8E%E6%8A%95%E4%BA%8640%E7%A5%A8%E8%80%8C%E6%B7%A1%E6%B7%A1%E6%8A%95%E4%BA%860",
          "hot": 0,
          "tag": ""
        },
        {
          "rank": 8,
          "title": "华为鸿蒙7首次亮相",
          "url": "https://s.weibo.com/weibo?q=%E5%8D%8E%E4%B8%BA%E9%B8%BF%E8%92%997%E9%A6%96%E6%AC%A1%E4%BA%AE%E7%9B%B8",
          "hot": 0,
          "tag": ""
        },
        {
          "rank": 9,
          "title": "给阿嬷的情书男主王彦桐签约壹心娱乐",
          "url": "https://s.weibo.com/weibo?q=%E7%BB%99%E9%98%BF%E5%AC%B7%E7%9A%84%E6%83%85%E4%B9%A6%E7%94%B7%E4%B8%BB%E7%8E%8B%E5%BD%A6%E6%A1%90%E7%AD%BE%E7%BA%A6%E5%A3%B9%E5%BF%83%E5%A8%B1%E4%B9%90",
          "hot": 0,
          "tag": ""
        },
        {
          "rank": 10,
          "title": "也是靠杨幂吃上这个夏天的红利了",
          "url": "https://s.weibo.com/weibo?q=%E4%B9%9F%E6%98%AF%E9%9D%A0%E6%9D%A8%E5%B9%82%E5%90%83%E4%B8%8A%E8%BF%99%E4%B8%AA%E5%A4%8F%E5%A4%A9%E7%9A%84%E7%BA%A2%E5%88%A9%E4%BA%86",
          "hot": 0,
          "tag": ""
        },
        {
          "rank": 11,
          "title": "因为饼干太好吃而察觉到不对劲",
          "url": "https://s.weibo.com/weibo?q=%E5%9B%A0%E4%B8%BA%E9%A5%BC%E5%B9%B2%E5%A4%AA%E5%A5%BD%E5%90%83%E8%80%8C%E5%AF%9F%E8%A7%89%E5%88%B0%E4%B8%8D%E5%AF%B9%E5%8A%B2",
          "hot": 0,
          "tag": ""
        },
        {
          "rank": 12,
          "title": "白鹿学历",
          "url": "https://s.weibo.com/weibo?q=%E7%99%BD%E9%B9%BF%E5%AD%A6%E5%8E%86",
          "hot": 0,
          "tag": ""
        },
        {
          "rank": 13,
          "title": "蒙淇淇是学法律的",
          "url": "https://s.weibo.com/weibo?q=%E8%92%99%E6%B7%87%E6%B7%87%E6%98%AF%E5%AD%A6%E6%B3%95%E5%BE%8B%E7%9A%84",
          "hot": 0,
          "tag": ""
        },
        {
          "rank": 14,
          "title": "A股",
          "url": "https://s.weibo.com/weibo?q=A%E8%82%A1",
          "hot": 0,
          "tag": ""
        },
        {
          "rank": 15,
          "title": "TFBOYS当年全员单吊一所大学",
          "url": "https://s.weibo.com/weibo?q=TFBOYS%E5%BD%93%E5%B9%B4%E5%85%A8%E5%91%98%E5%8D%95%E5%90%8A%E4%B8%80%E6%89%80%E5%A4%A7%E5%AD%A6",
          "hot": 0,
          "tag": ""
        },
        {
          "rank": 16,
          "title": "第一次见丑得像人的狗",
          "url": "https://s.weibo.com/weibo?q=%E7%AC%AC%E4%B8%80%E6%AC%A1%E8%A7%81%E4%B8%91%E5%BE%97%E5%83%8F%E4%BA%BA%E7%9A%84%E7%8B%97",
          "hot": 0,
          "tag": ""
        },
        {
          "rank": 17,
          "title": "鸿蒙6终端设备数突破6600万",
          "url": "https://s.weibo.com/weibo?q=%E9%B8%BF%E8%92%996%E7%BB%88%E7%AB%AF%E8%AE%BE%E5%A4%87%E6%95%B0%E7%AA%81%E7%A0%B46600%E4%B8%87",
          "hot": 0,
          "tag": ""
        },
        {
          "rank": 18,
          "title": "白鹿起诉甄姬不放瓜",
          "url": "https://s.weibo.com/weibo?q=%E7%99%BD%E9%B9%BF%E8%B5%B7%E8%AF%89%E7%94%84%E5%A7%AC%E4%B8%8D%E6%94%BE%E7%93%9C",
          "hot": 0,
          "tag": ""
        },
        {
          "rank": 19,
          "title": "鹿晗gapday音乐节",
          "url": "https://s.weibo.com/weibo?q=%E9%B9%BF%E6%99%97gapday%E9%9F%B3%E4%B9%90%E8%8A%82",
          "hot": 0,
          "tag": ""
        },
        {
          "rank": 20,
          "title": "21岁和26岁差距真的很大",
          "url": "https://s.weibo.com/weibo?q=21%E5%B2%81%E5%92%8C26%E5%B2%81%E5%B7%AE%E8%B7%9D%E7%9C%9F%E7%9A%84%E5%BE%88%E5%A4%A7",
          "hot": 0,
          "tag": ""
        },
        {
          "rank": 21,
          "title": "黄仁勋回应总穿皮夹克",
          "url": "https://s.weibo.com/weibo?q=%E9%BB%84%E4%BB%81%E5%8B%8B%E5%9B%9E%E5%BA%94%E6%80%BB%E7%A9%BF%E7%9A%AE%E5%A4%B9%E5%85%8B",
          "hot": 0,
          "tag": ""
        },
        {
          "rank": 22,
          "title": "王安宇以为手机被丁程鑫拿走",
          "url": "https://s.weibo.com/weibo?q=%E7%8E%8B%E5%AE%89%E5%AE%87%E4%BB%A5%E4%B8%BA%E6%89%8B%E6%9C%BA%E8%A2%AB%E4%B8%81%E7%A8%8B%E9%91%AB%E6%8B%BF%E8%B5%B0",
          "hot": 0,
          "tag": ""
        },
        {
          "rank": 23,
          "title": "歌手补位",
          "url": "https://s.weibo.com/weibo?q=%E6%AD%8C%E6%89%8B%E8%A1%A5%E4%BD%8D",
          "hot": 0,
          "tag": ""
        },
        {
          "rank": 24,
          "title": "起底中医号脉直播课",
          "url": "https://s.weibo.com/weibo?q=%E8%B5%B7%E5%BA%95%E4%B8%AD%E5%8C%BB%E5%8F%B7%E8%84%89%E7%9B%B4%E6%92%AD%E8%AF%BE",
          "hot": 0,
          "tag": ""
        },
        {
          "rank": 25,
          "title": "金靖不敢打张凌赫怕小核桃看到",
          "url": "https://s.weibo.com/weibo?q=%E9%87%91%E9%9D%96%E4%B8%8D%E6%95%A2%E6%89%93%E5%BC%A0%E5%87%8C%E8%B5%AB%E6%80%95%E5%B0%8F%E6%A0%B8%E6%A1%83%E7%9C%8B%E5%88%B0",
          "hot": 0,
          "tag": ""
        },
        {
          "rank": 26,
          "title": "迪丽热巴陈飞宇持续掉粉",
          "url": "https://s.weibo.com/weibo?q=%E8%BF%AA%E4%B8%BD%E7%83%AD%E5%B7%B4%E9%99%88%E9%A3%9E%E5%AE%87%E6%8C%81%E7%BB%AD%E6%8E%89%E7%B2%89",
          "hot": 0,
          "tag": ""
        },
        {
          "rank": 27,
          "title": "四六级翻译预测",
          "url": "https://s.weibo.com/weibo?q=%E5%9B%9B%E5%85%AD%E7%BA%A7%E7%BF%BB%E8%AF%91%E9%A2%84%E6%B5%8B",
          "hot": 0,
          "tag": ""
        }
      ],
      "updated": "2026-06-12T16:54:31.225934+08:00"
    },
    {
      "name": "知乎热榜",
      "items": [],
      "updated": "2026-06-12T16:54:33.790274+08:00",
      "error": "所有渠道均失败"
    },
    {
      "name": "百度热搜",
      "items": [
        {
          "rank": 1,
          "title": "友谊塔见证中朝友谊薪火相传",
          "url": "https://www.baidu.com/s?wd=友谊塔见证中朝友谊薪火相传",
          "hot": 0,
          "tag": ""
        },
        {
          "rank": 2,
          "title": "中国球迷墨西哥遭抢劫：被用枪抵头",
          "url": "https://www.baidu.com/s?wd=中国球迷墨西哥遭抢劫：被用枪抵头",
          "hot": 0,
          "tag": ""
        },
        {
          "rank": 3,
          "title": "一本居住证含金量有多高",
          "url": "https://www.baidu.com/s?wd=一本居住证含金量有多高",
          "hot": 0,
          "tag": ""
        },
        {
          "rank": 4,
          "title": "南方将进入强降雨集中期",
          "url": "https://www.baidu.com/s?wd=南方将进入强降雨集中期",
          "hot": 0,
          "tag": ""
        },
        {
          "rank": 5,
          "title": "世界杯第一批“受害者”已出现",
          "url": "https://www.baidu.com/s?wd=世界杯第一批“受害者”已出现",
          "hot": 0,
          "tag": ""
        },
        {
          "rank": 6,
          "title": "在耳朵里爆炸的耳机 同款销量超百万",
          "url": "https://www.baidu.com/s?wd=在耳朵里爆炸的耳机 同款销量超百万",
          "hot": 0,
          "tag": ""
        },
        {
          "rank": 7,
          "title": "网警披露未履行个人信息保护义务案",
          "url": "https://www.baidu.com/s?wd=网警披露未履行个人信息保护义务案",
          "hot": 0,
          "tag": ""
        },
        {
          "rank": 8,
          "title": "韩国2-1逆转捷克 亚洲球队首胜",
          "url": "https://www.baidu.com/s?wd=韩国2-1逆转捷克 亚洲球队首胜",
          "hot": 0,
          "tag": ""
        },
        {
          "rank": 9,
          "title": "金正恩向普京致贺电",
          "url": "https://www.baidu.com/s?wd=金正恩向普京致贺电",
          "hot": 0,
          "tag": ""
        },
        {
          "rank": 10,
          "title": "你吃的鱼可能吃过安眠药",
          "url": "https://www.baidu.com/s?wd=你吃的鱼可能吃过安眠药",
          "hot": 0,
          "tag": ""
        },
        {
          "rank": 11,
          "title": "谁说中国没进世界杯",
          "url": "https://www.baidu.com/s?wd=谁说中国没进世界杯",
          "hot": 0,
          "tag": ""
        },
        {
          "rank": 12,
          "title": "“公务车违停堵小区大门”不实",
          "url": "https://www.baidu.com/s?wd=“公务车违停堵小区大门”不实",
          "hot": 0,
          "tag": ""
        },
        {
          "rank": 13,
          "title": "男子带茅台乘高铁被拦下后豪饮整瓶",
          "url": "https://www.baidu.com/s?wd=男子带茅台乘高铁被拦下后豪饮整瓶",
          "hot": 0,
          "tag": ""
        },
        {
          "rank": 14,
          "title": "女子独游淹水古墓 陪葬品漂到脚边",
          "url": "https://www.baidu.com/s?wd=女子独游淹水古墓 陪葬品漂到脚边",
          "hot": 0,
          "tag": ""
        },
        {
          "rank": 15,
          "title": "人民日报评“和同事说话被开除”",
          "url": "https://www.baidu.com/s?wd=人民日报评“和同事说话被开除”",
          "hot": 0,
          "tag": ""
        },
        {
          "rank": 16,
          "title": "世界杯同款LABUBU卖爆了",
          "url": "https://www.baidu.com/s?wd=世界杯同款LABUBU卖爆了",
          "hot": 0,
          "tag": ""
        },
        {
          "rank": 17,
          "title": "世界杯唯一中超球员登场",
          "url": "https://www.baidu.com/s?wd=世界杯唯一中超球员登场",
          "hot": 0,
          "tag": ""
        },
        {
          "rank": 18,
          "title": "孙兴慜“亚洲一哥”变“亚洲一哥们”",
          "url": "https://www.baidu.com/s?wd=孙兴慜“亚洲一哥”变“亚洲一哥们”",
          "hot": 0,
          "tag": ""
        },
        {
          "rank": 19,
          "title": "中方回应制裁菲律宾国防部长",
          "url": "https://www.baidu.com/s?wd=中方回应制裁菲律宾国防部长",
          "hot": 0,
          "tag": ""
        },
        {
          "rank": 20,
          "title": "山西省委书记：深刻汲取惨痛教训",
          "url": "https://www.baidu.com/s?wd=山西省委书记：深刻汲取惨痛教训",
          "hot": 0,
          "tag": ""
        },
        {
          "rank": 21,
          "title": "伊朗大使馆发图讽刺世界杯是战争杯",
          "url": "https://www.baidu.com/s?wd=伊朗大使馆发图讽刺世界杯是战争杯",
          "hot": 0,
          "tag": ""
        },
        {
          "rank": 22,
          "title": "世界杯球队巡礼：加拿大队",
          "url": "https://www.baidu.com/s?wd=世界杯球队巡礼：加拿大队",
          "hot": 0,
          "tag": ""
        },
        {
          "rank": 23,
          "title": "王濛回应后悔参加《浪姐》",
          "url": "https://www.baidu.com/s?wd=王濛回应后悔参加《浪姐》",
          "hot": 0,
          "tag": ""
        },
        {
          "rank": 24,
          "title": "原来世界杯也假唱",
          "url": "https://www.baidu.com/s?wd=原来世界杯也假唱",
          "hot": 0,
          "tag": ""
        },
        {
          "rank": 25,
          "title": "韩媒批孙兴慜表现令人失望",
          "url": "https://www.baidu.com/s?wd=韩媒批孙兴慜表现令人失望",
          "hot": 0,
          "tag": ""
        },
        {
          "rank": 26,
          "title": "官方：根本就没有什么“特供酒”",
          "url": "https://www.baidu.com/s?wd=官方：根本就没有什么“特供酒”",
          "hot": 0,
          "tag": ""
        },
        {
          "rank": 27,
          "title": "阿根廷记者中断世界杯直播去追星",
          "url": "https://www.baidu.com/s?wd=阿根廷记者中断世界杯直播去追星",
          "hot": 0,
          "tag": ""
        },
        {
          "rank": 28,
          "title": "公路养护缺钱怪电车？专家呼吁",
          "url": "https://www.baidu.com/s?wd=公路养护缺钱怪电车？专家呼吁",
          "hot": 0,
          "tag": ""
        },
        {
          "rank": 29,
          "title": "7.52万箱“特供酒”被查获",
          "url": "https://www.baidu.com/s?wd=7.52万箱“特供酒”被查获",
          "hot": 0,
          "tag": ""
        },
        {
          "rank": 30,
          "title": "2026年世界杯五大“外星人”",
          "url": "https://www.baidu.com/s?wd=2026年世界杯五大“外星人”",
          "hot": 0,
          "tag": ""
        }
      ],
      "updated": "2026-06-12T16:54:36.524806+08:00"
    },
    {
      "name": "抖音热点",
      "items": [
        {
          "rank": 1,
          "title": "韩国2:1捷克",
          "url": "https://www.douyin.com/search/%E9%9F%A9%E5%9B%BD2%3A1%E6%8D%B7%E5%85%8B",
          "hot": 12129226,
          "tag": ""
        },
        {
          "rank": 2,
          "title": "加拿大波黑小组赛谁能取胜",
          "url": "https://www.douyin.com/search/%E5%8A%A0%E6%8B%BF%E5%A4%A7%E6%B3%A2%E9%BB%91%E5%B0%8F%E7%BB%84%E8%B5%9B%E8%B0%81%E8%83%BD%E5%8F%96%E8%83%9C",
          "hot": 10894075,
          "tag": ""
        },
        {
          "rank": 3,
          "title": "中国有望引领全球6G部署",
          "url": "https://www.douyin.com/search/%E4%B8%AD%E5%9B%BD%E6%9C%89%E6%9C%9B%E5%BC%95%E9%A2%86%E5%85%A8%E7%90%836G%E9%83%A8%E7%BD%B2",
          "hot": 10878160,
          "tag": ""
        },
        {
          "rank": 4,
          "title": "来许昌不吃杂炣等于白来",
          "url": "https://www.douyin.com/search/%E6%9D%A5%E8%AE%B8%E6%98%8C%E4%B8%8D%E5%90%83%E6%9D%82%E7%82%A3%E7%AD%89%E4%BA%8E%E7%99%BD%E6%9D%A5",
          "hot": 10874952,
          "tag": ""
        },
        {
          "rank": 5,
          "title": "官方明确电视剧演员署名规范",
          "url": "https://www.douyin.com/search/%E5%AE%98%E6%96%B9%E6%98%8E%E7%A1%AE%E7%94%B5%E8%A7%86%E5%89%A7%E6%BC%94%E5%91%98%E7%BD%B2%E5%90%8D%E8%A7%84%E8%8C%83",
          "hot": 10263977,
          "tag": ""
        },
        {
          "rank": 6,
          "title": "网警披露一起未履行个人信息保护义务案",
          "url": "https://www.douyin.com/search/%E7%BD%91%E8%AD%A6%E6%8A%AB%E9%9C%B2%E4%B8%80%E8%B5%B7%E6%9C%AA%E5%B1%A5%E8%A1%8C%E4%B8%AA%E4%BA%BA%E4%BF%A1%E6%81%AF%E4%BF%9D%E6%8A%A4%E4%B9%89%E5%8A%A1%E6%A1%88",
          "hot": 9992110,
          "tag": ""
        },
        {
          "rank": 7,
          "title": "墨西哥2:0南非赢下揭幕战",
          "url": "https://www.douyin.com/search/%E5%A2%A8%E8%A5%BF%E5%93%A52%3A0%E5%8D%97%E9%9D%9E%E8%B5%A2%E4%B8%8B%E6%8F%AD%E5%B9%95%E6%88%98",
          "hot": 8725394,
          "tag": ""
        },
        {
          "rank": 8,
          "title": "这个榴莲馒头看起来很诱人",
          "url": "https://www.douyin.com/search/%E8%BF%99%E4%B8%AA%E6%A6%B4%E8%8E%B2%E9%A6%92%E5%A4%B4%E7%9C%8B%E8%B5%B7%E6%9D%A5%E5%BE%88%E8%AF%B1%E4%BA%BA",
          "hot": 8621204,
          "tag": ""
        },
        {
          "rank": 9,
          "title": "周五看球热辣开启",
          "url": "https://www.douyin.com/search/%E5%91%A8%E4%BA%94%E7%9C%8B%E7%90%83%E7%83%AD%E8%BE%A3%E5%BC%80%E5%90%AF",
          "hot": 8247952,
          "tag": ""
        },
        {
          "rank": 10,
          "title": "现场观赛世界杯是什么体验",
          "url": "https://www.douyin.com/search/%E7%8E%B0%E5%9C%BA%E8%A7%82%E8%B5%9B%E4%B8%96%E7%95%8C%E6%9D%AF%E6%98%AF%E4%BB%80%E4%B9%88%E4%BD%93%E9%AA%8C",
          "hot": 7830438,
          "tag": ""
        },
        {
          "rank": 11,
          "title": "常州一直升机尾部断裂迫降草坪",
          "url": "https://www.douyin.com/search/%E5%B8%B8%E5%B7%9E%E4%B8%80%E7%9B%B4%E5%8D%87%E6%9C%BA%E5%B0%BE%E9%83%A8%E6%96%AD%E8%A3%82%E8%BF%AB%E9%99%8D%E8%8D%89%E5%9D%AA",
          "hot": 7827923,
          "tag": ""
        },
        {
          "rank": 12,
          "title": "日本男足队长宣布退役",
          "url": "https://www.douyin.com/search/%E6%97%A5%E6%9C%AC%E7%94%B7%E8%B6%B3%E9%98%9F%E9%95%BF%E5%AE%A3%E5%B8%83%E9%80%80%E5%BD%B9",
          "hot": 7820973,
          "tag": ""
        },
        {
          "rank": 13,
          "title": "墨西哥球迷氛围太嗨了",
          "url": "https://www.douyin.com/search/%E5%A2%A8%E8%A5%BF%E5%93%A5%E7%90%83%E8%BF%B7%E6%B0%9B%E5%9B%B4%E5%A4%AA%E5%97%A8%E4%BA%86",
          "hot": 7797109,
          "tag": ""
        },
        {
          "rank": 14,
          "title": "关于西瓜的谣言你都听过哪些",
          "url": "https://www.douyin.com/search/%E5%85%B3%E4%BA%8E%E8%A5%BF%E7%93%9C%E7%9A%84%E8%B0%A3%E8%A8%80%E4%BD%A0%E9%83%BD%E5%90%AC%E8%BF%87%E5%93%AA%E4%BA%9B",
          "hot": 7779206,
          "tag": ""
        },
        {
          "rank": 15,
          "title": "演员白鹿方发表声明",
          "url": "https://www.douyin.com/search/%E6%BC%94%E5%91%98%E7%99%BD%E9%B9%BF%E6%96%B9%E5%8F%91%E8%A1%A8%E5%A3%B0%E6%98%8E",
          "hot": 7766897,
          "tag": ""
        },
        {
          "rank": 16,
          "title": "端午放假3天不调休高速不免费",
          "url": "https://www.douyin.com/search/%E7%AB%AF%E5%8D%88%E6%94%BE%E5%81%873%E5%A4%A9%E4%B8%8D%E8%B0%83%E4%BC%91%E9%AB%98%E9%80%9F%E4%B8%8D%E5%85%8D%E8%B4%B9",
          "hot": 7765016,
          "tag": ""
        },
        {
          "rank": 17,
          "title": "用想要问问你敢不敢打开甄嬛传",
          "url": "https://www.douyin.com/search/%E7%94%A8%E6%83%B3%E8%A6%81%E9%97%AE%E9%97%AE%E4%BD%A0%E6%95%A2%E4%B8%8D%E6%95%A2%E6%89%93%E5%BC%80%E7%94%84%E5%AC%9B%E4%BC%A0",
          "hot": 7759339,
          "tag": ""
        },
        {
          "rank": 18,
          "title": "许昕暖心回应考生心愿",
          "url": "https://www.douyin.com/search/%E8%AE%B8%E6%98%95%E6%9A%96%E5%BF%83%E5%9B%9E%E5%BA%94%E8%80%83%E7%94%9F%E5%BF%83%E6%84%BF",
          "hot": 7753212,
          "tag": ""
        },
        {
          "rank": 19,
          "title": "唐梓坏端端的突然变好了",
          "url": "https://www.douyin.com/search/%E5%94%90%E6%A2%93%E5%9D%8F%E7%AB%AF%E7%AB%AF%E7%9A%84%E7%AA%81%E7%84%B6%E5%8F%98%E5%A5%BD%E4%BA%86",
          "hot": 7749783,
          "tag": ""
        },
        {
          "rank": 20,
          "title": "世界杯揭幕战预言家来了",
          "url": "https://www.douyin.com/search/%E4%B8%96%E7%95%8C%E6%9D%AF%E6%8F%AD%E5%B9%95%E6%88%98%E9%A2%84%E8%A8%80%E5%AE%B6%E6%9D%A5%E4%BA%86",
          "hot": 7746711,
          "tag": ""
        },
        {
          "rank": 21,
          "title": "水果姐世界杯开幕表演预热抖音",
          "url": "https://www.douyin.com/search/%E6%B0%B4%E6%9E%9C%E5%A7%90%E4%B8%96%E7%95%8C%E6%9D%AF%E5%BC%80%E5%B9%95%E8%A1%A8%E6%BC%94%E9%A2%84%E7%83%AD%E6%8A%96%E9%9F%B3",
          "hot": 7742667,
          "tag": ""
        },
        {
          "rank": 22,
          "title": "哈兰德也是听上挪威的森林了",
          "url": "https://www.douyin.com/search/%E5%93%88%E5%85%B0%E5%BE%B7%E4%B9%9F%E6%98%AF%E5%90%AC%E4%B8%8A%E6%8C%AA%E5%A8%81%E7%9A%84%E6%A3%AE%E6%9E%97%E4%BA%86",
          "hot": 7741192,
          "tag": ""
        },
        {
          "rank": 23,
          "title": "Angel你懂我的眼泪",
          "url": "https://www.douyin.com/search/Angel%E4%BD%A0%E6%87%82%E6%88%91%E7%9A%84%E7%9C%BC%E6%B3%AA",
          "hot": 7739597,
          "tag": ""
        },
        {
          "rank": 24,
          "title": "世界杯精彩程度下降了吗",
          "url": "https://www.douyin.com/search/%E4%B8%96%E7%95%8C%E6%9D%AF%E7%B2%BE%E5%BD%A9%E7%A8%8B%E5%BA%A6%E4%B8%8B%E9%99%8D%E4%BA%86%E5%90%97",
          "hot": 7739008,
          "tag": ""
        },
        {
          "rank": 25,
          "title": "世界杯志愿者第一视角来了",
          "url": "https://www.douyin.com/search/%E4%B8%96%E7%95%8C%E6%9D%AF%E5%BF%97%E6%84%BF%E8%80%85%E7%AC%AC%E4%B8%80%E8%A7%86%E8%A7%92%E6%9D%A5%E4%BA%86",
          "hot": 7736839,
          "tag": ""
        },
        {
          "rank": 26,
          "title": "柳智敏金玟庭现场看世界杯",
          "url": "https://www.douyin.com/search/%E6%9F%B3%E6%99%BA%E6%95%8F%E9%87%91%E7%8E%9F%E5%BA%AD%E7%8E%B0%E5%9C%BA%E7%9C%8B%E4%B8%96%E7%95%8C%E6%9D%AF",
          "hot": 7731424,
          "tag": ""
        },
        {
          "rank": 27,
          "title": "邓超体验一日跨省送餐员",
          "url": "https://www.douyin.com/search/%E9%82%93%E8%B6%85%E4%BD%93%E9%AA%8C%E4%B8%80%E6%97%A5%E8%B7%A8%E7%9C%81%E9%80%81%E9%A4%90%E5%91%98",
          "hot": 7730758,
          "tag": ""
        },
        {
          "rank": 28,
          "title": "林树和王浩宇立起了世界杯预测flag",
          "url": "https://www.douyin.com/search/%E6%9E%97%E6%A0%91%E5%92%8C%E7%8E%8B%E6%B5%A9%E5%AE%87%E7%AB%8B%E8%B5%B7%E4%BA%86%E4%B8%96%E7%95%8C%E6%9D%AF%E9%A2%84%E6%B5%8Bflag",
          "hot": 7728736,
          "tag": ""
        },
        {
          "rank": 29,
          "title": "哈兰德抖音粉丝数超曼城",
          "url": "https://www.douyin.com/search/%E5%93%88%E5%85%B0%E5%BE%B7%E6%8A%96%E9%9F%B3%E7%B2%89%E4%B8%9D%E6%95%B0%E8%B6%85%E6%9B%BC%E5%9F%8E",
          "hot": 7722182,
          "tag": ""
        },
        {
          "rank": 30,
          "title": "新疆小羊哥发抖音感谢网友关注",
          "url": "https://www.douyin.com/search/%E6%96%B0%E7%96%86%E5%B0%8F%E7%BE%8A%E5%93%A5%E5%8F%91%E6%8A%96%E9%9F%B3%E6%84%9F%E8%B0%A2%E7%BD%91%E5%8F%8B%E5%85%B3%E6%B3%A8",
          "hot": 7715455,
          "tag": ""
        }
      ],
      "updated": "2026-06-12T16:54:37.893834+08:00"
    },
    {
      "name": "B站热门",
      "items": [
        {
          "rank": 1,
          "title": "《明日方舟：终末地》版本情报 | 危机合约先导PV与「寻遗散记」更新",
          "url": "https://www.bilibili.com/video/BV1gtEB6VEfm",
          "hot": 765161,
          "tag": "手机游戏"
        },
        {
          "rank": 2,
          "title": "《弧光猎人》弧光测试PV&国服事件预告｜星火燎原",
          "url": "https://www.bilibili.com/video/BV11GEv6dEvW",
          "hot": 1040310,
          "tag": "单机游戏"
        },
        {
          "rank": 3,
          "title": "有什么比精神小妹爱上纯情男大的故事更狗血",
          "url": "https://www.bilibili.com/video/BV1xfEq6AEWd",
          "hot": 2417898,
          "tag": "搞笑"
        },
        {
          "rank": 4,
          "title": "【纪录片】地球·劫后重生 中配版01 火山炼狱",
          "url": "https://www.bilibili.com/video/BV11SEY6XERX",
          "hot": 398704,
          "tag": "科学·探索·自然"
        },
        {
          "rank": 5,
          "title": "【某幻】《盛世天下》再返深宫，活下来！",
          "url": "https://www.bilibili.com/video/BV1W4EE6GECF",
          "hot": 5290507,
          "tag": "影视剪辑"
        },
        {
          "rank": 6,
          "title": "都2026年了，AI产品到底是真有用还是智商税？",
          "url": "https://www.bilibili.com/video/BV1aZER6oEGN",
          "hot": 792837,
          "tag": "数码"
        },
        {
          "rank": 7,
          "title": "净化班味",
          "url": "https://www.bilibili.com/video/BV127Eq6cEVQ",
          "hot": 1475140,
          "tag": "日常"
        },
        {
          "rank": 8,
          "title": "星际超级荒诞动画喜剧！《外星小偷里贝》第03话：上岸星球【UP动画】",
          "url": "https://www.bilibili.com/video/BV1KkEK6CELv",
          "hot": 2422601,
          "tag": "小剧场"
        },
        {
          "rank": 9,
          "title": "认为自己旅游运差时可以看看我.",
          "url": "https://www.bilibili.com/video/BV18VED63EBi",
          "hot": 3074691,
          "tag": "日常"
        },
        {
          "rank": 10,
          "title": "【独家】《将夜》第9集 风雨入夜【4月国创】",
          "url": "https://www.bilibili.com/video/BV13AEZ6wE7B",
          "hot": 492189,
          "tag": "国产动画"
        },
        {
          "rank": 11,
          "title": "懒人为了“顺手”俩字，到底能做多少收纳？",
          "url": "https://www.bilibili.com/video/BV1otE96tE36",
          "hot": 1517521,
          "tag": "家居房产"
        },
        {
          "rank": 12,
          "title": "动态视频｜吸进身体的二手烟，到底有多脏？",
          "url": "https://www.bilibili.com/video/BV17YEv6VEUx",
          "hot": 1072174,
          "tag": "科学科普"
        },
        {
          "rank": 13,
          "title": "我和TheShy吃过饭，我可以打上单职业吗？",
          "url": "https://www.bilibili.com/video/BV1YCEq6VEjU",
          "hot": 229020,
          "tag": "电子竞技"
        },
        {
          "rank": 14,
          "title": "当你想养狗，不同国家爸妈都是啥反应？最后一个，来照镜子！",
          "url": "https://www.bilibili.com/video/BV18UEv6wEzp",
          "hot": 879194,
          "tag": "小剧场"
        },
        {
          "rank": 15,
          "title": "瑞斯拜考前50分系列 四六级必考词汇 26年新版",
          "url": "https://www.bilibili.com/video/BV1FAEi6DEiT",
          "hot": 571418,
          "tag": "校园学习"
        },
        {
          "rank": 16,
          "title": "现实情况不可能有这种事，你不干也会有别人干",
          "url": "https://www.bilibili.com/video/BV1QeE96WE2m",
          "hot": 948394,
          "tag": "影视剪辑"
        },
        {
          "rank": 17,
          "title": "别叫霞姐叫“侠姐”",
          "url": "https://www.bilibili.com/video/BV1uWEe68E3e",
          "hot": 373403,
          "tag": "短片"
        },
        {
          "rank": 18,
          "title": "如何骗走CIA三百根金条",
          "url": "https://www.bilibili.com/video/BV1oQEe6gEFg",
          "hot": 507526,
          "tag": "人文历史"
        },
        {
          "rank": 19,
          "title": "家人们觉得这车洗完还能开吗？",
          "url": "https://www.bilibili.com/video/BV1BfEQ6bESF",
          "hot": 559461,
          "tag": "汽车生活"
        },
        {
          "rank": 20,
          "title": "【纪录片】一招一食 第一回 刀",
          "url": "https://www.bilibili.com/video/BV1i2EX64E7F",
          "hot": 1660949,
          "tag": "社会·美食·旅行"
        },
        {
          "rank": 21,
          "title": "你是谁，请支持羞羞獭【听伊莫不emo 01】",
          "url": "https://www.bilibili.com/video/BV1siEo6SEk8",
          "hot": 1800542,
          "tag": "综合"
        },
        {
          "rank": 22,
          "title": "《绝区零》维琳娜角色展示 | 茶会一如既往",
          "url": "https://www.bilibili.com/video/BV1FzEr6YExJ",
          "hot": 367783,
          "tag": "手机游戏"
        },
        {
          "rank": 23,
          "title": "全新爽搜图！新式免保！新式房卡！多结局解密！核电站它来了！「三角洲S9赛季」",
          "url": "https://www.bilibili.com/video/BV1aCEv6vE1z",
          "hot": 1528751,
          "tag": "网络游戏"
        },
        {
          "rank": 24,
          "title": "当90后家长上门道歉",
          "url": "https://www.bilibili.com/video/BV1v9ER68Ehn",
          "hot": 1596868,
          "tag": "搞笑"
        },
        {
          "rank": 25,
          "title": "在上海吃到了玫瑰腐乳肉，长江这一路的酸甜苦辣咸脆鲜香咱也尝遍了！",
          "url": "https://www.bilibili.com/video/BV1GfEe6iE3x",
          "hot": 828597,
          "tag": "日常"
        },
        {
          "rank": 26,
          "title": "4款复古开罐器实测【Rescue_Restore官方】",
          "url": "https://www.bilibili.com/video/BV12XEv6bEjp",
          "hot": 1275443,
          "tag": "科工机械"
        },
        {
          "rank": 27,
          "title": "女巫的解药~",
          "url": "https://www.bilibili.com/video/BV1uhEi6YEJC",
          "hot": 457576,
          "tag": "搞笑"
        },
        {
          "rank": 28,
          "title": "居然把脚给人看",
          "url": "https://www.bilibili.com/video/BV12sEC6SEBs",
          "hot": 117826,
          "tag": "搞笑"
        },
        {
          "rank": 29,
          "title": "一口气看完，整栋房子建造过程",
          "url": "https://www.bilibili.com/video/BV1ja766sEzR",
          "hot": 695958,
          "tag": "家居房产"
        },
        {
          "rank": 30,
          "title": "原来导演才是真正的跑男！",
          "url": "https://www.bilibili.com/video/BV1SGEq6eEAE",
          "hot": 675918,
          "tag": "影视杂谈"
        }
      ],
      "updated": "2026-06-12T16:54:38.704487+08:00"
    },
    {
      "name": "IT之家",
      "items": [
        {
          "rank": 1,
          "title": "曝华为鸿蒙 HarmonyOS 7 系统的卓易通 App 已升级安卓 16",
          "url": "https://www.ithome.com/0/963/603.htm",
          "hot": 0,
          "tag": ""
        },
        {
          "rank": 2,
          "title": "维咖首款双 8kHz“铝坨坨”机械键盘 NUT75 今晚发售，399 元起",
          "url": "https://www.ithome.com/0/963/601.htm",
          "hot": 0,
          "tag": ""
        },
        {
          "rank": 3,
          "title": "赛力斯张兴海：受存储芯片涨价等影响，问界平均一辆车面临 1.5 万-2 万块钱的成本涨幅",
          "url": "https://www.ithome.com/0/963/600.htm",
          "hot": 0,
          "tag": ""
        },
        {
          "rank": 4,
          "title": "大众召回 2 辆进口宾利欧陆系列汽车：轮毂固定螺母可能未安装到位",
          "url": "https://www.ithome.com/0/963/587.htm",
          "hot": 0,
          "tag": ""
        },
        {
          "rank": 5,
          "title": "鸿蒙 HarmonyOS 7 正式发布：从“万物互联”正式迈进“Agent 时代”，华为 Mate90 系列今秋首发搭载",
          "url": "https://www.ithome.com/0/963/594.htm",
          "hot": 0,
          "tag": ""
        },
        {
          "rank": 6,
          "title": "2027 款丰田赛那 MPV 上市：搭载华为 HMS for Car 与小米车端硬件接口，权益价 24.28 万元起",
          "url": "https://www.ithome.com/0/963/590.htm",
          "hot": 0,
          "tag": ""
        },
        {
          "rank": 7,
          "title": "华为何刚：鸿蒙 HarmonyOS 7 正式版将在今年秋季向消费者开放",
          "url": "https://www.ithome.com/0/963/586.htm",
          "hot": 0,
          "tag": ""
        },
        {
          "rank": 8,
          "title": "华为龚体：鸿蒙 HarmonyOS 6 升级率达 98%",
          "url": "https://www.ithome.com/0/963/581.htm",
          "hot": 0,
          "tag": ""
        },
        {
          "rank": 9,
          "title": "韩国混凝土配送停运，影响三星、SK 海力士部分芯片工厂扩建项目",
          "url": "https://www.ithome.com/0/963/576.htm",
          "hot": 0,
          "tag": ""
        },
        {
          "rank": 10,
          "title": "国产神话武侠题材独立游戏《太吾绘卷：天幕心帷》鸿蒙版官宣 6 月 17 日上线",
          "url": "https://www.ithome.com/0/963/572.htm",
          "hot": 0,
          "tag": ""
        },
        {
          "rank": 11,
          "title": "咪咕视频 x 华为鸿蒙首发手机直播专业体育赛事，用于中超、苏超、粤超",
          "url": "https://www.ithome.com/0/963/569.htm",
          "hot": 0,
          "tag": ""
        },
        {
          "rank": 12,
          "title": "NextSilicon 规划 64、128 核心企业级 RISC-V 处理器，预计 2028 年初上市",
          "url": "https://www.ithome.com/0/963/563.htm",
          "hot": 0,
          "tag": ""
        },
        {
          "rank": 13,
          "title": "抖音：开展“恶意营销号”治理，累计处置违规账号 387.4 万个",
          "url": "https://www.ithome.com/0/963/559.htm",
          "hot": 0,
          "tag": ""
        },
        {
          "rank": 14,
          "title": "华为联合 UWA 发布业界首个空间影像标准：空间菁彩影像",
          "url": "https://www.ithome.com/0/963/558.htm",
          "hot": 0,
          "tag": ""
        },
        {
          "rank": 15,
          "title": "华为鸿蒙 HarmonyOS 7 沉浸光感更沉浸，IT之家登上 HDC 2026",
          "url": "https://www.ithome.com/0/963/554.htm",
          "hot": 0,
          "tag": ""
        },
        {
          "rank": 16,
          "title": "vivo X Fold6 搭载全新电脑模式：连上大屏界面更接近 PC，手机能变触控板",
          "url": "https://www.ithome.com/0/963/552.htm",
          "hot": 0,
          "tag": ""
        },
        {
          "rank": 17,
          "title": "赛力斯张兴海：有人说增程是脱裤子放屁，数据证明它解决了用户的充电难和里程焦虑",
          "url": "https://www.ithome.com/0/963/551.htm",
          "hot": 0,
          "tag": ""
        },
        {
          "rank": 18,
          "title": "AI 指纹识别 + 九种开锁方式：小米智能门锁 G100 国补后 1099 → 358 元",
          "url": "https://www.ithome.com/0/963/547.htm",
          "hot": 0,
          "tag": ""
        },
        {
          "rank": 19,
          "title": "TrendForce 数据：台积电晶圆代工市占率 2026Q1 达 72.3%",
          "url": "https://www.ithome.com/0/963/546.htm",
          "hot": 0,
          "tag": ""
        },
        {
          "rank": 20,
          "title": "蔚来法务部：市面上抄袭仿冒 NOMI 现象愈演愈烈，已对多家公司提起诉讼",
          "url": "https://www.ithome.com/0/963/543.htm",
          "hot": 0,
          "tag": ""
        },
        {
          "rank": 21,
          "title": "比亚迪汽车客服热线宣布升级为 950858，号码更短更便捷",
          "url": "https://www.ithome.com/0/963/537.htm",
          "hot": 0,
          "tag": ""
        },
        {
          "rank": 22,
          "title": "蔚来李斌：新能源车减重需要勇气，冲刺阶段每“减肥”一公斤成本约千元",
          "url": "https://www.ithome.com/0/963/536.htm",
          "hot": 0,
          "tag": ""
        },
        {
          "rank": 23,
          "title": "华为 AI 眼镜 × 小艺看世界官宣 8 月上线，辅助视障用户探索世界",
          "url": "https://www.ithome.com/0/963/535.htm",
          "hot": 0,
          "tag": ""
        },
        {
          "rank": 24,
          "title": "泡泡玛特自研手游《梦想家园》宣布 8 月 12 日停止运营，今日起关闭全平台充值、新用户注册",
          "url": "https://www.ithome.com/0/963/534.htm",
          "hot": 0,
          "tag": ""
        },
        {
          "rank": 25,
          "title": "手机秒变游戏掌机，华为鸿蒙 HarmonyOS 7 带来控显分离功能",
          "url": "https://www.ithome.com/0/963/533.htm",
          "hot": 0,
          "tag": ""
        },
        {
          "rank": 26,
          "title": "新型智能夹克问世，可从空气中直接提取饮用水",
          "url": "https://www.ithome.com/0/963/528.htm",
          "hot": 0,
          "tag": ""
        },
        {
          "rank": 27,
          "title": "华为鸿蒙 HarmonyOS 7 推出数字资产继承，用户可自主选择继承范围和继承人",
          "url": "https://www.ithome.com/0/963/525.htm",
          "hot": 0,
          "tag": ""
        },
        {
          "rank": 28,
          "title": "游戏《红色沙漠》全球累计销量突破 600 万份：耗时 83 天，创韩国单机游戏历史纪录",
          "url": "https://www.ithome.com/0/963/523.htm",
          "hot": 0,
          "tag": ""
        },
        {
          "rank": 29,
          "title": "亚马逊创始人贝索斯：AI 像把刀，有危险但不能直接“一禁了之”",
          "url": "https://www.ithome.com/0/963/519.htm",
          "hot": 0,
          "tag": ""
        },
        {
          "rank": 30,
          "title": "“追窗”30 年新里程碑：开源 ReactOS 系统成功运行 Windows 游戏《半条命》",
          "url": "https://www.ithome.com/0/963/517.htm",
          "hot": 0,
          "tag": ""
        }
      ],
      "updated": "2026-06-12T16:54:44.642200+08:00"
    }
  ]
}